Lab_7/t_ff.vhd
library IEEE;
use IEEE.STD_LOGIC_1164.ALL;

entity T_FF is
    port (
        CLK : in std_logic;
        T   : in std_logic;
        Q   : out std_logic;
        QB  : out std_logic
    );
end entity T_FF;

architecture Behavioral of T_FF is
    signal Q_int : std_logic := '0';
begin
    process (CLK)
    begin
        if rising_edge(CLK) then
            if T = '1' then
                Q_int <= not Q_int;
            end if;
        end if;
    end process;

    Q <= Q_int;
    QB <= not Q_int;
end architecture Behavioral;

Lab_7/jk_ff.vhd
library IEEE;
use IEEE.STD_LOGIC_1164.ALL;

entity JK_FF is
    port (
        CLK : in std_logic;
        J   : in std_logic;
        K   : in std_logic;
        Q   : out std_logic;
        QB  : out std_logic
    );
end entity JK_FF;

architecture Behavioral of JK_FF is
    signal Q_int : std_logic := '0';
begin
    process (CLK)
    begin
        if rising_edge(CLK) then
            if J = '0' and K = '0' then
                null;
            elsif J = '0' and K = '1' then
                Q_int <= '0';
            elsif J = '1' and K = '0' then
                Q_int <= '1';
            else
                Q_int <= not Q_int;
            end if;
        end if;
    end process;

    Q <= Q_int;
    QB <= not Q_int;
end architecture Behavioral;

Lab_7/d_ff.vhd
library IEEE;
use IEEE.STD_LOGIC_1164.ALL;

entity D_FF is
    port (
        CLK : in std_logic;
        D   : in std_logic;
        Q   : out std_logic;
        QB  : out std_logic
    );
end entity D_FF;

architecture Behavioral of D_FF is
    signal Q_int : std_logic := '0';
begin
    process (CLK)
    begin
        if rising_edge(CLK) then
            Q_int <= D;
        end if;
    end process;

    Q <= Q_int;
    QB <= not Q_int;
end architecture Behavioral;

Lab_7/sr_ff.vhd
library IEEE;
use IEEE.STD_LOGIC_1164.ALL;

entity SR_FF is
    port (
        CLK : in std_logic;
        S   : in std_logic;
        R   : in std_logic;
        Q   : out std_logic;
        QB  : out std_logic
    );
end entity SR_FF;

architecture Behavioral of SR_FF is
    signal Q_int : std_logic := '0';
begin
    process (CLK)
    begin
        if rising_edge(CLK) then
            if S = '0' and R = '0' then
                null;
            elsif S = '0' and R = '1' then
                Q_int <= '0';
            elsif S = '1' and R = '0' then
                Q_int <= '1';
            end if;
        end if;
    end process;

    Q <= Q_int;
    QB <= not Q_int;
end architecture Behavioral;

Lab_7/ff_tb.vhd
library IEEE;
use IEEE.STD_LOGIC_1164.ALL;

entity FF_TB is
end entity FF_TB;

architecture Simulation of FF_TB is
    signal CLK : std_logic := '0';
    signal S, R : std_logic := '0';
    signal D : std_logic := '0';
    signal J, K : std_logic := '0';
    signal T : std_logic := '0';
    signal Q_SR, Q_D, Q_JK, Q_T : std_logic;
    signal QB_SR, QB_D, QB_JK, QB_T : std_logic;

    constant CLK_PERIOD : time := 20 ns;
begin
    CLK <= not CLK after CLK_PERIOD / 2;

    U1 : entity work.SR_FF port map (CLK, S, R, Q_SR, QB_SR);
    U2 : entity work.D_FF port map (CLK, D, Q_D, QB_D);
    U3 : entity work.JK_FF port map (CLK, J, K, Q_JK, QB_JK);
    U4 : entity work.T_FF port map (CLK, T, Q_T, QB_T);

    STIMULUS : process
    begin
        S <= '1'; R <= '0'; wait for 40 ns;
        S <= '0'; R <= '1'; wait for 40 ns;
        S <= '0'; R <= '0'; wait for 40 ns;

        D <= '1'; wait for 40 ns;
        D <= '0'; wait for 40 ns;

        J <= '1'; K <= '0'; wait for 40 ns;
        J <= '1'; K <= '1'; wait for 40 ns;
        J <= '0'; K <= '1'; wait for 40 ns;

        T <= '1'; wait for 80 ns;
        T <= '0'; wait for 40 ns;

        wait;
    end process;
end architecture Simulation;

Lab_7/flipflops.vcd
$date
  Tue Jul 07 10:59:57 2026
$end
$version
  GHDL v0
$end
$timescale
  1 fs
$end
$scope module standard $end
$upscope $end
$scope module std_logic_1164 $end
$upscope $end
$scope module ff_tb $end
$var reg 1 ! clk $end
$var reg 1 " s $end
$var reg 1 # r $end
$var reg 1 $ d $end
$var reg 1 % j $end
$var reg 1 & k $end
$var reg 1 ' t $end
$var reg 1 ( q_sr $end
$var reg 1 ) q_d $end
$var reg 1 * q_jk $end
$var reg 1 + q_t $end
$var reg 1 , qb_sr $end
$var reg 1 - qb_d $end
$var reg 1 . qb_jk $end
$var reg 1 / qb_t $end
$scope module u1 $end
$var reg 1 0 clk $end
$var reg 1 1 s $end
$var reg 1 2 r $end
$var reg 1 3 q $end
$var reg 1 4 qb $end
$var reg 1 5 q_int $end
$upscope $end
$scope module u2 $end
$var reg 1 6 clk $end
$var reg 1 7 d $end
$var reg 1 8 q $end
$var reg 1 9 qb $end
$var reg 1 : q_int $end
$upscope $end
$scope module u3 $end
$var reg 1 ; clk $end
$var reg 1 < j $end
$var reg 1 = k $end
$var reg 1 > q $end
$var reg 1 ? qb $end
$var reg 1 @ q_int $end
$upscope $end
$scope module u4 $end
$var reg 1 A clk $end
$var reg 1 B t $end
$var reg 1 C q $end
$var reg 1 D qb $end
$var reg 1 E q_int $end
$upscope $end
$upscope $end
$enddefinitions $end
#0
0!
1"
0#
0$
0%
0&
0'
0(
0)
0*
0+
1,
1-
1.
1/
00
11
02
03
14
05
06
07
08
19
0:
0;
0<
0=
0>
1?
0@
0A
0B
0C
1D
0E
#10000000
1!
1(
0,
10
13
04
15
16
1;
1A
#20000000
0!
00
06
0;
0A
#30000000
1!
10
16
1;
1A
#40000000
0!
0"
1#
00
01
12
06
0;
0A
#50000000
1!
0(
1,
10
03
14
05
16
1;
1A
#60000000
0!
00
06
0;
0A
#70000000
1!
10
16
1;
1A
#80000000
0!
0#
00
02
06
0;
0A
#90000000
1!
10
16
1;
1A
#100000000
0!
00
06
0;
0A
#110000000
1!
10
16
1;
1A
#120000000
0!
1$
00
06
17
0;
0A
#130000000
1!
1)
0-
10
16
18
09
1:
1;
1A
#140000000
0!
00
06
0;
0A
#150000000
1!
10
16
1;
1A
#160000000
0!
0$
00
06
07
0;
0A
#170000000
1!
0)
1-
10
16
08
19
0:
1;
1A
#180000000
0!
00
06
0;
0A
#190000000
1!
10
16
1;
1A
#200000000
0!
1%
00
06
0;
1<
0A
#210000000
1!
1*
0.
10
16
1;
1>
0?
1@
1A
#220000000
0!
00
06
0;
0A
#230000000
1!
10
16
1;
1A
#240000000
0!
1&
00
06
0;
1=
0A
#250000000
1!
0*
1.
10
16
1;
0>
1?
0@
1A
#260000000
0!
00
06
0;
0A
#270000000
1!
1*
0.
10
16
1;
1>
0?
1@
1A
#280000000
0!
0%
00
06
0;
0<
0A
#290000000
1!
0*
1.
10
16
1;
0>
1?
0@
1A
#300000000
0!
00
06
0;
0A
#310000000
1!
10
16
1;
1A
#320000000
0!
1'
00
06
0;
0A
1B
#330000000
1!
1+
0/
10
16
1;
1A
1C
0D
1E
#340000000
0!
00
06
0;
0A
#350000000
1!
0+
1/
10
16
1;
1A
0C
1D
0E
#360000000
0!
00
06
0;
0A
#370000000
1!
1+
0/
10
16
1;
1A
1C
0D
1E
#380000000
0!
00
06
0;
0A
#390000000
1!
0+
1/
10
16
1;
1A
0C
1D
0E
#400000000
0!
0'
00
06
0;
0A
0B
